README
setup.cfg
setup.py
pydiffbot/__init__.py
pydiffbot/diffbot.py
pydiffbot/exceptions.py
pydiffbot.egg-info/PKG-INFO
pydiffbot.egg-info/SOURCES.txt
pydiffbot.egg-info/dependency_links.txt
pydiffbot.egg-info/top_level.txt