Metadata-Version: 1.1
Name: pydiffbot
Version: 0.1
Summary: A diffbot API wrapper for Python
Home-page: https://github.com/makmac213/
Author: Mark Allan B Meriales
Author-email: mark.meriales@gmail.com
License: UNKNOWN
Download-URL: https://github.com/makmac213/PyDiffBot
Platform: UNKNOWN
Classifier: Development Status :: 4 - Beta
Classifier: Intended Audience :: Developers
Classifier: Natural Language :: English
Classifier: Programming Language :: Python
Classifier: License :: Freeware
